{"1628384": {"fg3a": 0.0, "fg3m": 0.0}, "1626157": {"fg3a": 0.0, "fg3m": 0.0}, "1630574": {"fg3a": 0.0, "fg3m": 0.0}, "1628969": {"fg3a": 0.0, "fg3m": 0.0}, "1628973": {"fg3a": 0.0, "fg3m": 0.0}, "1627824": {"fg3a": 0.0, "fg3m": 0.0}, "1630540": {"fg3a": 0.0, "fg3m": 0.0}, "1641998": {"fg3a": 0.0, "fg3m": 0.0}, "1629013": {"fg3a": 0.0, "fg3m": 0.0}, "203903": {"fg3a": 0.0, "fg3m": 0.0}, "1642278": {"fg3a": 0.0, "fg3m": 0.0}, "1630596": {"fg3a": 0.0, "fg3m": 0.0}, "1642281": {"fg3a": 0.0, "fg3m": 0.0}, "1628386": {"fg3a": 0.0, "fg3m": 0.0}, "1630241": {"fg3a": 0.0, "fg3m": 0.0}, "1628378": {"fg3a": 0.0, "fg3m": 0.0}, "1628366": {"fg3a": 0.0, "fg3m": 0.0}, "1629731": {"fg3a": 0.0, "fg3m": 0.0}, "1641854": {"fg3a": 0.0, "fg3m": 0.0}, "1626204": {"fg3a": 0.0, "fg3m": 0.0}, "1642878": {"fg3a": 0.0, "fg3m": 0.0}, "1629023": {"fg3a": 0.0, "fg3m": 0.0}, "203076": {"fg3a": 0.0, "fg3m": 0.0}, "1641726": {"fg3a": 0.0, "fg3m": 0.0}, "202691": {"fg3a": 0.0, "fg3m": 0.0}, "1642843": {"fg3a": 0.0, "fg3m": 0.0}, "1630230": {"fg3a": 0.0, "fg3m": 0.0}, "1631108": {"fg3a": 0.0, "fg3m": 0.0}, "1626156": {"fg3a": 0.0, "fg3m": 0.0}, "1642948": {"fg3a": 0.0, "fg3m": 0.0}, "203939": {"fg3a": 0.0, "fg3m": 0.0}, "1630314": {"fg3a": 0.0, "fg3m": 0.0}, "1630702": {"fg3a": 0.0, "fg3m": 0.0}, "1628997": {"fg3a": 0.0, "fg3m": 0.0}}